LICENSE.txt
README.md
setup.cfg
setup.py
splitio/__init__.py
splitio/exceptions.py
splitio/factories.py
splitio/impressions.py
splitio/key.py
splitio/spec.py
splitio/version.py
splitio/api/__init__.py
splitio/api/auth.py
splitio/api/client.py
splitio/api/commons.py
splitio/api/events.py
splitio/api/impressions.py
splitio/api/segments.py
splitio/api/splits.py
splitio/api/telemetry.py
splitio/client/__init__.py
splitio/client/client.py
splitio/client/config.py
splitio/client/factory.py
splitio/client/input_validator.py
splitio/client/key.py
splitio/client/listener.py
splitio/client/localhost.py
splitio/client/manager.py
splitio/client/util.py
splitio/engine/__init__.py
splitio/engine/evaluator.py
splitio/engine/filters.py
splitio/engine/splitters.py
splitio/engine/telemetry.py
splitio/engine/cache/__init__.py
splitio/engine/cache/lru.py
splitio/engine/hashfns/__init__.py
splitio/engine/hashfns/legacy.py
splitio/engine/hashfns/murmur3py.py
splitio/engine/impressions/__init__.py
splitio/engine/impressions/adapters.py
splitio/engine/impressions/impressions.py
splitio/engine/impressions/manager.py
splitio/engine/impressions/strategies.py
splitio/engine/impressions/unique_keys_tracker.py
splitio/models/__init__.py
splitio/models/datatypes.py
splitio/models/events.py
splitio/models/fallback_config.py
splitio/models/fallback_treatment.py
splitio/models/impressions.py
splitio/models/notification.py
splitio/models/rule_based_segments.py
splitio/models/segments.py
splitio/models/splits.py
splitio/models/telemetry.py
splitio/models/token.py
splitio/models/grammar/__init__.py
splitio/models/grammar/condition.py
splitio/models/grammar/partitions.py
splitio/models/grammar/matchers/__init__.py
splitio/models/grammar/matchers/base.py
splitio/models/grammar/matchers/keys.py
splitio/models/grammar/matchers/misc.py
splitio/models/grammar/matchers/numeric.py
splitio/models/grammar/matchers/prerequisites.py
splitio/models/grammar/matchers/rule_based_segment.py
splitio_client.egg-info/PKG-INFO
splitio_client.egg-info/SOURCES.txt
splitio_client.egg-info/dependency_links.txt
splitio_client.egg-info/requires.txt
splitio_client.egg-info/top_level.txt