Metadata-Version: 2.1
Name: splitio-client
Version: 10.5.1
Summary: Split.io Python Client
Home-page: https://github.com/splitio/python-client
Download-URL: https://github.com/splitio/python-client/tarball/10.5.1
Author: Patricio Echague, Sebastian Arrubia
Author-email: pato@split.io, sebastian@split.io
License: Apache License 2.0
Classifier: Environment :: Console
Classifier: Intended Audience :: Developers
Classifier: Programming Language :: Python
Classifier: Programming Language :: Python :: 2
Classifier: Programming Language :: Python :: 3
Classifier: Topic :: Software Development :: Libraries
Provides-Extra: test
Provides-Extra: redis
Provides-Extra: uwsgi
Provides-Extra: cpphash
Provides-Extra: asyncio
Provides-Extra: kerberos
License-File: LICENSE.txt
